DrawTick/__init__.py
DrawTick/common.py
DrawTick/download_tick.py
DrawTick/draw_tick.py
DrawTick/tick_data
DrawTick/zhangting.py
src/__init__.py
src/draw_tick.py
DrawTick-0.0.7.dist-info/METADATA
DrawTick-0.0.7.dist-info/WHEEL
DrawTick-0.0.7.dist-info/top_level.txt
DrawTick-0.0.7.dist-info/RECORD
